{
  "results": [
    {
      "seed": 42,
      "num_threads": 4,
      "beam_width": 32,
      "num_queries": 150000,
      "catapults_enabled": true,
      "elapsed_secs": 27.335290577,
      "qps": 5487.411943819265,
      "checksum": 74243762419,
      "avg_dists_computed": 667.54374,
      "avg_nodes_visited": 33.88768666666667,
      "work_avoided": 366.1155533333333,
      "searches_with_catapults": 146565,
      "catapult_usage_pct": 97.71,
      "avg_catapults_added": 0.9771
    },
    {
      "seed": 43,
      "num_threads": 4,
      "beam_width": 32,
      "num_queries": 150000,
      "catapults_enabled": true,
      "elapsed_secs": 26.957011242,
      "qps": 5564.415084944379,
      "checksum": 74313831919,
      "avg_dists_computed": 665.7608466666667,
      "avg_nodes_visited": 33.877453333333335,
      "work_avoided": 366.0862666666667,
      "searches_with_catapults": 145791,
      "catapult_usage_pct": 97.194,
      "avg_catapults_added": 0.97194
    },
    {
      "seed": 44,
      "num_threads": 4,
      "beam_width": 32,
      "num_queries": 150000,
      "catapults_enabled": true,
      "elapsed_secs": 26.918575581,
      "qps": 5572.360229412542,
      "checksum": 74419266338,
      "avg_dists_computed": 666.0950066666667,
      "avg_nodes_visited": 33.86206,
      "work_avoided": 366.3974333333333,
      "searches_with_catapults": 145931,
      "catapult_usage_pct": 97.28733333333334,
      "avg_catapults_added": 0.9728733333333334
    },
    {
      "seed": 45,
      "num_threads": 4,
      "beam_width": 32,
      "num_queries": 150000,
      "catapults_enabled": true,
      "elapsed_secs": 27.58000624,
      "qps": 5438.7224823194965,
      "checksum": 74325279068,
      "avg_dists_computed": 667.9087933333333,
      "avg_nodes_visited": 33.88386666666667,
      "work_avoided": 366.1143133333333,
      "searches_with_catapults": 146788,
      "catapult_usage_pct": 97.85866666666666,
      "avg_catapults_added": 0.9785866666666667
    },
    {
      "seed": 46,
      "num_threads": 4,
      "beam_width": 32,
      "num_queries": 150000,
      "catapults_enabled": true,
      "elapsed_secs": 27.324068305,
      "qps": 5489.6656795632325,
      "checksum": 74294873409,
      "avg_dists_computed": 668.6315533333334,
      "avg_nodes_visited": 33.91693333333333,
      "work_avoided": 366.6207866666667,
      "searches_with_catapults": 146846,
      "catapult_usage_pct": 97.89733333333334,
      "avg_catapults_added": 0.9789733333333334
    }
  ]
}